dramatiq_kafka/__init__.py
dramatiq_kafka/broker.py
dramatiq_kafka-0.1.9.dist-info/METADATA
dramatiq_kafka-0.1.9.dist-info/WHEEL
dramatiq_kafka-0.1.9.dist-info/RECORD
