Metadata-Version: 2.1
Name: dramatiq-kafka
Version: 0.1.9
Summary: A Kafka broker for Dramatiq.
Author: Viktor Babchanik
Author-email: vbabchanik@ucdavis.edu
Requires-Python: >=3.8,<4.0
Classifier: Programming Language :: Python :: 3
Classifier: Programming Language :: Python :: 3.8
Classifier: Programming Language :: Python :: 3.9
Classifier: Programming Language :: Python :: 3.10
Classifier: Programming Language :: Python :: 3.11
Requires-Dist: kafka-python (==2.0.2)
